{
"type": "FeatureCollection",
"name": "localidades",
"crs": { "type": "name", "properties": { "name": "urn:ogc:def:crs:OGC:1.3:CRS84" } },
"features": [
{ "type": "Feature", "properties": { "name": "015", "distrito": "POZOS" }, "geometry": { "type": "Point", "coordinates": [ -84.188595361985307, 9.947813937747096 ] } },
{ "type": "Feature", "properties": { "name": "016", "distrito": "POZOS" }, "geometry": { "type": "Point", "coordinates": [ -84.189606122360189, 9.961473294317949 ] } },
{ "type": "Feature", "properties": { "name": "017", "distrito": "POZOS" }, "geometry": { "type": "Point", "coordinates": [ -84.188611160837709, 9.962504179204018 ] } },
{ "type": "Feature", "properties": { "name": "018", "distrito": "POZOS" }, "geometry": { "type": "Point", "coordinates": [ -84.18364222462381, 9.963281073270585 ] } },
{ "type": "Feature", "properties": { "name": "008", "distrito": "POZOS" }, "geometry": { "type": "Point", "coordinates": [ -84.18388931409855, 9.965149368071499 ] } },
{ "type": "Feature", "properties": { "name": "009", "distrito": "POZOS" }, "geometry": { "type": "Point", "coordinates": [ -84.189753227670479, 9.964218423769347 ] } },
{ "type": "Feature", "properties": { "name": "010", "distrito": "POZOS" }, "geometry": { "type": "Point", "coordinates": [ -84.191015251589775, 9.959310596190681 ] } },
{ "type": "Feature", "properties": { "name": "011", "distrito": "POZOS" }, "geometry": { "type": "Point", "coordinates": [ -84.193048877387412, 9.958985772195328 ] } },
{ "type": "Feature", "properties": { "name": "012", "distrito": "POZOS" }, "geometry": { "type": "Point", "coordinates": [ -84.205720791303207, 9.958053211527291 ] } },
{ "type": "Feature", "properties": { "name": "013", "distrito": "POZOS" }, "geometry": { "type": "Point", "coordinates": [ -84.205000464628014, 9.959271055009037 ] } },
{ "type": "Feature", "properties": { "name": "001", "distrito": "SANTA ANA" }, "geometry": { "type": "Point", "coordinates": [ -84.18477977866813, 9.939978763206195 ] } },
{ "type": "Feature", "properties": { "name": "002", "distrito": "SANTA ANA" }, "geometry": { "type": "Point", "coordinates": [ -84.185373991654473, 9.938913639146767 ] } },
{ "type": "Feature", "properties": { "name": "023", "distrito": "BRASIL" }, "geometry": { "type": "Point", "coordinates": [ -84.225225134578039, 9.942287787404753 ] } },
{ "type": "Feature", "properties": { "name": "024", "distrito": "BRASIL" }, "geometry": { "type": "Point", "coordinates": [ -84.225434843984104, 9.943911421723207 ] } },
{ "type": "Feature", "properties": { "name": "022", "distrito": "PIEDADES" }, "geometry": { "type": "Point", "coordinates": [ -84.219727516815965, 9.930369056468724 ] } },
{ "type": "Feature", "properties": { "name": "019", "distrito": "URUCA" }, "geometry": { "type": "Point", "coordinates": [ -84.195764186256241, 9.914284823978575 ] } },
{ "type": "Feature", "properties": { "name": "020", "distrito": "URUCA" }, "geometry": { "type": "Point", "coordinates": [ -84.196509120258312, 9.919926766085062 ] } },
{ "type": "Feature", "properties": { "name": "005", "distrito": "SALITRAL" }, "geometry": { "type": "Point", "coordinates": [ -84.180941541315221, 9.90552287677736 ] } },
{ "type": "Feature", "properties": { "name": "006", "distrito": "SALITRAL" }, "geometry": { "type": "Point", "coordinates": [ -84.177042735326694, 9.905139356963236 ] } },
{ "type": "Feature", "properties": { "name": "007", "distrito": "SALITRAL" }, "geometry": { "type": "Point", "coordinates": [ -84.171771479228639, 9.888295926644421 ] } },
{ "type": "Feature", "properties": { "name": "003", "distrito": "SANTA ANA" }, "geometry": { "type": "Point", "coordinates": [ -84.177105222896103, 9.925077851438758 ] } },
{ "type": "Feature", "properties": { "name": "004", "distrito": "SANTA ANA" }, "geometry": { "type": "Point", "coordinates": [ -84.176795326322434, 9.926315570208073 ] } },
{ "type": "Feature", "properties": { "name": "021", "distrito": "URUCA" }, "geometry": { "type": "Point", "coordinates": [ -84.187399541190146, 9.927925337903133 ] } },
{ "type": "Feature", "properties": { "name": "014", "distrito": "POZOS" }, "geometry": { "type": "Point", "coordinates": [ -84.185095579365623, 9.94300922604315 ] } },
{ "type": "Feature", "properties": { "name": null, "distrito": null }, "geometry": { "type": "Point", "coordinates": [ -84.188662595708351, 9.963485383233719 ] } }
]
}
